{
  "companies": [
    {
      "id": 1,
      "name": "TechStart Inc.",
      "foundedDate": "2022-01-15",
      "industry": "Technology",
      "status": "active",
      "lastValuation": "2024-01-10",
      "totalFunding": 5000000,
      "employees": 25,
      "description": "AI-powered software platform for enterprise automation",
      "location": "San Francisco, CA",
      "email": "contact@techstart.com",
      "phone": "+1 (555) 123-4567",
      "contact_person": "John Smith",
      "updated_at": "2025-09-14T09:51:03.380Z"
    },
    {
      "id": 2,
      "name": "InnovateCorp",
      "foundedDate": "2021-06-20",
      "industry": "Healthcare",
      "status": "Active",
      "lastValuation": "2024-01-08",
      "totalFunding": 12000000,
      "employees": 45,
      "description": "Medical device company developing surgical robotics"
    },
    {
      "id": 3,
      "name": "StartupXYZ",
      "foundedDate": "2023-03-10",
      "industry": "Fintech",
      "status": "Active",
      "lastValuation": "2024-01-05",
      "totalFunding": 2500000,
      "employees": 15,
      "description": "Digital banking platform for small businesses"
    }
  ],
  "shareClasses": [
    {
      "id": 1,
      "companyId": 1,
      "shareType": "common",
      "name": "Common Stock",
      "roundDate": "2022-01-15",
      "sharesOutstanding": 8000000,
      "pricePerShare": 0.125,
      "preferenceType": "non-participating",
      "lpMultiple": 1,
      "seniority": 2,
      "participationCap": null,
      "conversionRatio": 1,
      "dividendsDeclared": false,
      "dividendsRate": null,
      "dividendsType": null,
      "pik": false
    },
    {
      "id": 2,
      "companyId": 1,
      "shareType": "preferred",
      "name": "Series A Preferred",
      "roundDate": "2023-06-01",
      "sharesOutstanding": 2000000,
      "pricePerShare": 2.5,
      "preferenceType": "participating",
      "lpMultiple": 1,
      "seniority": 1,
      "participationCap": null,
      "conversionRatio": 1,
      "dividendsDeclared": true,
      "dividendsRate": 0.08,
      "dividendsType": "cumulative",
      "pik": false
    },
    {
      "id": 3,
      "companyId": 1,
      "shareType": "preferred",
      "name": "Series B Preferred",
      "roundDate": "2024-03-15",
      "sharesOutstanding": 1500000,
      "pricePerShare": 4,
      "preferenceType": "participating-with-cap",
      "lpMultiple": 1.5,
      "seniority": 0,
      "participationCap": 3,
      "conversionRatio": 1,
      "dividendsDeclared": true,
      "dividendsRate": 0.1,
      "dividendsType": "non-cumulative",
      "pik": true
    }
  ],
  "valuations": [
    {
      "id": 1,
      "companyId": 1,
      "title": "Series A 409A Valuation",
      "valuationType": "409A",
      "status": "completed",
      "valuationDate": "2024-01-10",
      "fairMarketValue": 2.5,
      "totalValue": 25000000,
      "methodology": "DCF",
      "purpose": "Stock Option Grants",
      "createdAt": "2024-01-08T10:00:00Z",
      "updatedAt": "2024-01-10T15:30:00Z",
      "assumptions": {
        "general": {
          "company_name": 0,
          "valuation_date": 2025,
          "fiscal_year_end": 12,
          "industry": 0,
          "stage": 0,
          "years_in_operation": 0
        },
        "financial_metrics": {
          "revenue_current": 2500000,
          "revenue_prior": 1800000,
          "ebitda_current": -500000,
          "gross_margin": 75,
          "operating_margin": -15,
          "burn_rate": 150000,
          "cash_balance": 3200000,
          "debt_outstanding": 0,
          "runway_months": 21
        },
        "growth_assumptions": {
          "revenue_growth_y1": 25,
          "revenue_growth_y2": 20,
          "revenue_growth_y3": 15,
          "revenue_growth_y4": 12,
          "revenue_growth_y5": 10,
          "terminal_growth_rate": 2.5,
          "target_ebitda_margin": 15
        },
        "discount_rates": {
          "wacc": 12,
          "cost_of_equity": 15,
          "cost_of_debt": 6,
          "tax_rate": 21,
          "risk_free_rate": 3.63,
          "market_risk_premium": 7,
          "size_premium": 3,
          "company_specific_premium": 2,
          "minority_interest_discount": 15
        },
        "volatility_assumptions": {
          "equity_volatility": 60,
          "asset_volatility": 45,
          "time_to_liquidity": 5,
          "probability_ipo": 10,
          "probability_ma": 30,
          "probability_dissolution": 5
        },
        "market_approach": {
          "revenue_multiple": 3.5,
          "ebitda_multiple": 12,
          "ps_ratio": 4,
          "market_approach_weight": 30,
          "income_approach_weight": 70
        },
        "backsolve": {
          "last_round_date": "2024-03-15",
          "last_round_amount": 6000000,
          "last_round_premoney": 20000000,
          "last_round_price": 4.00,
          "backsolve_volatility": 55
        }
      },
      "cap_table": {
        "shareClasses": [
          {
            "id": 1,
            "companyId": 1,
            "shareType": "common",
            "name": "Common Stock",
            "roundDate": "2022-01-15",
            "sharesOutstanding": 8000000,
            "pricePerShare": 0.0001,
            "preferenceType": "non-participating",
            "lpMultiple": 1,
            "seniority": 2,
            "participationCap": null,
            "conversionRatio": 1,
            "dividendsDeclared": false,
            "dividendsRate": null,
            "dividendsType": null,
            "pik": false,
            "amountInvested": 800,
            "totalLP": 800,
            "asConvertedShares": 8000000,
            "totalDividends": 0
          },
          {
            "id": 2,
            "companyId": 1,
            "shareType": "preferred",
            "name": "Series A Preferred",
            "roundDate": "2023-06-01",
            "sharesOutstanding": 2000000,
            "pricePerShare": 2.5,
            "preferenceType": "participating",
            "lpMultiple": 1,
            "seniority": 2,
            "participationCap": null,
            "conversionRatio": 1,
            "dividendsDeclared": false,
            "dividendsRate": 0.08,
            "dividendsType": "cumulative",
            "pik": false,
            "amountInvested": 5000000,
            "totalLP": 5000000,
            "asConvertedShares": 2000000,
            "totalDividends": 0
          },
          {
            "id": 3,
            "companyId": 1,
            "shareType": "preferred",
            "name": "Series B Preferred",
            "roundDate": "2024-03-15",
            "sharesOutstanding": 1500000,
            "pricePerShare": 4,
            "preferenceType": "participating-with-cap",
            "lpMultiple": 1.5,
            "seniority": 1,
            "participationCap": 3,
            "conversionRatio": 1,
            "dividendsDeclared": false,
            "dividendsRate": 0.1,
            "dividendsType": "non-cumulative",
            "pik": true,
            "amountInvested": 6000000,
            "totalLP": 9000000,
            "asConvertedShares": 1500000,
            "totalDividends": 0
          }
        ],
        "options": [
          {
            "id": "1757827366022",
            "numOptions": 250000,
            "exercisePrice": 1.25,
            "type": "Options"
          },
          {
            "id": "1757827475392",
            "numOptions": 350000,
            "exercisePrice": 1.36,
            "type": "Options"
          }
        ],
        "updated_at": "2025-09-14T13:39:24.660Z"
      },
      "updated_at": "2025-09-18T19:20:49.871Z"
    },
    {
      "id": 2,
      "companyId": 2,
      "title": "Pre-Money Valuation",
      "valuationType": "Pre-Money",
      "status": "in_progress",
      "valuationDate": "2024-01-15",
      "fairMarketValue": 4.75,
      "totalValue": 50000000,
      "methodology": "Market",
      "purpose": "Transaction Support",
      "createdAt": "2024-01-12T09:15:00Z",
      "updatedAt": "2024-01-15T11:20:00Z"
    },
    {
      "id": 3,
      "companyId": 3,
      "title": "409A Valuation - Seed",
      "valuationType": "409A",
      "status": "draft",
      "valuationDate": "2024-01-20",
      "fairMarketValue": 1.25,
      "totalValue": 8000000,
      "methodology": "Asset",
      "purpose": "Financial Reporting",
      "createdAt": "2024-01-18T14:30:00Z",
      "updatedAt": "2024-01-19T16:45:00Z"
    }
  ],
  "nextId": {
    "companies": 4,
    "shareClasses": 3,
    "valuations": 4
  }
}